MirahezeBots_jsonparser/__init__.py
MirahezeBots_jsonparser/jsonparser/__init__.py
MirahezeBots_jsonparser-1.0.4.dist-info/LICENSE
MirahezeBots_jsonparser-1.0.4.dist-info/METADATA
MirahezeBots_jsonparser-1.0.4.dist-info/WHEEL
MirahezeBots_jsonparser-1.0.4.dist-info/top_level.txt
MirahezeBots_jsonparser-1.0.4.dist-info/RECORD
